inmanta_plugins/docker/__init__.py
inmanta_plugins/docker/setup.cfg
inmanta_plugins/docker/model/_init.cf
inmanta_plugins/docker/templates/docker-sysconfig.tmpl
tests/test_module.py
inmanta_module_docker-0.4.8.dist-info/METADATA
inmanta_module_docker-0.4.8.dist-info/WHEEL
inmanta_module_docker-0.4.8.dist-info/top_level.txt
inmanta_module_docker-0.4.8.dist-info/RECORD
