Metadata-Version: 2.1
Name: inmanta-module-docker
Version: 0.4.8
Summary: Module to manage docker based containers
Home-page: UNKNOWN
License: Apache 2.0
Platform: UNKNOWN
Requires-Dist: inmanta-module-ip
Requires-Dist: inmanta-module-std
Requires-Dist: docker-py (==1.10.6)
